Metadata-Version: 2.1
Name: cubao-meshcat
Version: 0.3.3
Summary: WebGL-based visualizer for 3D geometries and scenes
Home-page: https://github.com/cubao/meshcat-python
Author: tzx
Author-email: dvorak4tzx@gmail.com
License: MIT
Platform: UNKNOWN
